README.rst
setup.py
aplite/__init__.py
aplite/__main__.py
aplite/cli.py
aplite.egg-info/PKG-INFO
aplite.egg-info/SOURCES.txt
aplite.egg-info/dependency_links.txt
aplite.egg-info/entry_points.txt
aplite.egg-info/top_level.txt