Metadata-Version: 1.0
Name: aplite
Version: 0.1.dev1
Summary: UNKNOWN
Home-page: https://github.com/barell/aplite
Author: UNKNOWN
Author-email: UNKNOWN
License: MIT
Platform: UNKNOWN
